{
  "success": true,
  "orders": [
    {
      "_id": "68334d74c2f30c001cb26ede",
      "ingredients": [
        "643d69a5c3f7b9001cfa093d",
        "643d69a5c3f7b9001cfa093e",
        "643d69a5c3f7b9001cfa093d"
      ],
      "status": "done",
      "name": "Флюоресцентный люминесцентный бургер",
      "createdAt": "2025-05-25T17:03:48.313Z",
      "updatedAt": "2025-05-25T17:03:49.045Z",
      "number": 78750
    },
    {
      "_id": "68334d82c2f30c001cb26ee0",
      "ingredients": [
        "643d69a5c3f7b9001cfa093d",
        "643d69a5c3f7b9001cfa093e",
        "643d69a5c3f7b9001cfa0940",
        "643d69a5c3f7b9001cfa093d"
      ],
      "status": "done",
      "name": "Флюоресцентный люминесцентный метеоритный бургер",
      "createdAt": "2025-05-25T17:04:02.671Z",
      "updatedAt": "2025-05-25T17:04:03.339Z",
      "number": 78751
    },
    {
      "_id": "683351b9c2f30c001cb26eec",
      "ingredients": [
        "643d69a5c3f7b9001cfa093c",
        "643d69a5c3f7b9001cfa093e",
        "643d69a5c3f7b9001cfa093c"
      ],
      "status": "done",
      "name": "Краторный люминесцентный бургер",
      "createdAt": "2025-05-25T17:22:01.944Z",
      "updatedAt": "2025-05-25T17:22:02.862Z",
      "number": 78754
    },
    {
      "_id": "68335d9dc2f30c001cb26f17",
      "ingredients": [
        "643d69a5c3f7b9001cfa093d",
        "643d69a5c3f7b9001cfa0947",
        "643d69a5c3f7b9001cfa0947",
        "643d69a5c3f7b9001cfa093d"
      ],
      "status": "done",
      "name": "Флюоресцентный фалленианский бургер",
      "createdAt": "2025-05-25T18:12:45.327Z",
      "updatedAt": "2025-05-25T18:12:46.279Z",
      "number": 78760
    },
    {
      "_id": "683362cdc2f30c001cb26f34",
      "ingredients": [
        "643d69a5c3f7b9001cfa093c",
        "643d69a5c3f7b9001cfa0946",
        "643d69a5c3f7b9001cfa0949",
        "643d69a5c3f7b9001cfa093c"
      ],
      "status": "done",
      "name": "Краторный экзо-плантаго минеральный бургер",
      "createdAt": "2025-05-25T18:34:53.682Z",
      "updatedAt": "2025-05-25T18:34:54.544Z",
      "number": 78767
    },
    {
      "_id": "68336dcfc2f30c001cb26f88",
      "ingredients": [
        "643d69a5c3f7b9001cfa093d",
        "643d69a5c3f7b9001cfa093e",
        "643d69a5c3f7b9001cfa093d"
      ],
      "status": "done",
      "name": "Флюоресцентный люминесцентный бургер",
      "createdAt": "2025-05-25T19:21:51.025Z",
      "updatedAt": "2025-05-25T19:21:52.336Z",
      "number": 78781
    },
    {
      "_id": "683376d5c2f30c001cb26fd4",
      "ingredients": [
        "643d69a5c3f7b9001cfa093d",
        "643d69a5c3f7b9001cfa093e",
        "643d69a5c3f7b9001cfa093d"
      ],
      "status": "done",
      "name": "Флюоресцентный люминесцентный бургер",
      "createdAt": "2025-05-25T20:00:21.403Z",
      "updatedAt": "2025-05-25T20:00:22.138Z",
      "number": 78786
    },
    {
      "_id": "68337eadc2f30c001cb2700c",
      "ingredients": [
        "643d69a5c3f7b9001cfa093d",
        "643d69a5c3f7b9001cfa093e",
        "643d69a5c3f7b9001cfa093d"
      ],
      "status": "done",
      "name": "Флюоресцентный люминесцентный бургер",
      "createdAt": "2025-05-25T20:33:49.366Z",
      "updatedAt": "2025-05-25T20:33:50.125Z",
      "number": 78791
    },
    {
      "_id": "68337eddc2f30c001cb2700f",
      "ingredients": [
        "643d69a5c3f7b9001cfa093d",
        "643d69a5c3f7b9001cfa093e",
        "643d69a5c3f7b9001cfa0940",
        "643d69a5c3f7b9001cfa093d"
      ],
      "status": "done",
      "name": "Флюоресцентный люминесцентный метеоритный бургер",
      "createdAt": "2025-05-25T20:34:37.564Z",
      "updatedAt": "2025-05-25T20:34:38.280Z",
      "number": 78792
    },
    {
      "_id": "68345791c2f30c001cb2722f",
      "ingredients": [
        "643d69a5c3f7b9001cfa093d",
        "643d69a5c3f7b9001cfa093e",
        "643d69a5c3f7b9001cfa093d"
      ],
      "status": "done",
      "name": "Флюоресцентный люминесцентный бургер",
      "createdAt": "2025-05-26T11:59:13.093Z",
      "updatedAt": "2025-05-26T11:59:13.852Z",
      "number": 78841
    },
    {
      "_id": "683457acc2f30c001cb27232",
      "ingredients": [
        "643d69a5c3f7b9001cfa093d",
        "643d69a5c3f7b9001cfa093d"
      ],
      "status": "done",
      "name": "Флюоресцентный бургер",
      "createdAt": "2025-05-26T11:59:40.141Z",
      "updatedAt": "2025-05-26T11:59:40.866Z",
      "number": 78842
    },
    {
      "_id": "683457c2c2f30c001cb27234",
      "ingredients": [
        "643d69a5c3f7b9001cfa093d",
        "643d69a5c3f7b9001cfa093d"
      ],
      "status": "done",
      "name": "Флюоресцентный бургер",
      "createdAt": "2025-05-26T12:00:02.098Z",
      "updatedAt": "2025-05-26T12:00:02.870Z",
      "number": 78843
    },
    {
      "_id": "683457fac2f30c001cb27235",
      "ingredients": [
        "643d69a5c3f7b9001cfa093d",
        "643d69a5c3f7b9001cfa093d"
      ],
      "status": "done",
      "name": "Флюоресцентный бургер",
      "createdAt": "2025-05-26T12:00:58.019Z",
      "updatedAt": "2025-05-26T12:00:58.765Z",
      "number": 78844
    },
    {
      "_id": "6834580ec2f30c001cb27236",
      "ingredients": [
        "643d69a5c3f7b9001cfa093d",
        "643d69a5c3f7b9001cfa093d"
      ],
      "status": "done",
      "name": "Флюоресцентный бургер",
      "createdAt": "2025-05-26T12:01:18.468Z",
      "updatedAt": "2025-05-26T12:01:19.194Z",
      "number": 78845
    },
    {
      "_id": "68345871c2f30c001cb27237",
      "ingredients": [
        "643d69a5c3f7b9001cfa093d",
        "643d69a5c3f7b9001cfa093e",
        "643d69a5c3f7b9001cfa093d"
      ],
      "status": "done",
      "name": "Флюоресцентный люминесцентный бургер",
      "createdAt": "2025-05-26T12:02:57.883Z",
      "updatedAt": "2025-05-26T12:02:58.663Z",
      "number": 78846
    },
    {
      "_id": "683458d7c2f30c001cb2723b",
      "ingredients": [
        "643d69a5c3f7b9001cfa093d",
        "643d69a5c3f7b9001cfa093e",
        "643d69a5c3f7b9001cfa093d"
      ],
      "status": "done",
      "name": "Флюоресцентный люминесцентный бургер",
      "createdAt": "2025-05-26T12:04:39.954Z",
      "updatedAt": "2025-05-26T12:04:40.777Z",
      "number": 78847
    },
    {
      "_id": "68345911c2f30c001cb2723d",
      "ingredients": [
        "643d69a5c3f7b9001cfa093d",
        "643d69a5c3f7b9001cfa093e",
        "643d69a5c3f7b9001cfa093d"
      ],
      "status": "done",
      "name": "Флюоресцентный люминесцентный бургер",
      "createdAt": "2025-05-26T12:05:37.538Z",
      "updatedAt": "2025-05-26T12:05:38.192Z",
      "number": 78849
    },
    {
      "_id": "683459aec2f30c001cb27245",
      "ingredients": [
        "643d69a5c3f7b9001cfa093d",
        "643d69a5c3f7b9001cfa093e",
        "643d69a5c3f7b9001cfa093d"
      ],
      "status": "done",
      "name": "Флюоресцентный люминесцентный бургер",
      "createdAt": "2025-05-26T12:08:14.739Z",
      "updatedAt": "2025-05-26T12:08:15.526Z",
      "number": 78850
    },
    {
      "_id": "683459e9c2f30c001cb27247",
      "ingredients": [
        "643d69a5c3f7b9001cfa093d",
        "643d69a5c3f7b9001cfa093e",
        "643d69a5c3f7b9001cfa093d"
      ],
      "status": "done",
      "name": "Флюоресцентный люминесцентный бургер",
      "createdAt": "2025-05-26T12:09:13.673Z",
      "updatedAt": "2025-05-26T12:09:14.396Z",
      "number": 78851
    },
    {
      "_id": "68345a16c2f30c001cb27248",
      "ingredients": [
        "643d69a5c3f7b9001cfa093d",
        "643d69a5c3f7b9001cfa093f",
        "643d69a5c3f7b9001cfa093d"
      ],
      "status": "done",
      "name": "Флюоресцентный бессмертный бургер",
      "createdAt": "2025-05-26T12:09:58.236Z",
      "updatedAt": "2025-05-26T12:09:58.992Z",
      "number": 78852
    },
    {
      "_id": "68345a71c2f30c001cb2724a",
      "ingredients": [
        "643d69a5c3f7b9001cfa093d",
        "643d69a5c3f7b9001cfa093d"
      ],
      "status": "done",
      "name": "Флюоресцентный бургер",
      "createdAt": "2025-05-26T12:11:29.639Z",
      "updatedAt": "2025-05-26T12:11:30.428Z",
      "number": 78853
    },
    {
      "_id": "68345b7ac2f30c001cb2724f",
      "ingredients": [
        "643d69a5c3f7b9001cfa093c",
        "643d69a5c3f7b9001cfa0947",
        "643d69a5c3f7b9001cfa093c"
      ],
      "status": "done",
      "name": "Краторный фалленианский бургер",
      "createdAt": "2025-05-26T12:15:54.176Z",
      "updatedAt": "2025-05-26T12:15:54.891Z",
      "number": 78855
    },
    {
      "_id": "68345ba8c2f30c001cb27250",
      "ingredients": [
        "643d69a5c3f7b9001cfa093d",
        "643d69a5c3f7b9001cfa0940",
        "643d69a5c3f7b9001cfa093d"
      ],
      "status": "done",
      "name": "Флюоресцентный метеоритный бургер",
      "createdAt": "2025-05-26T12:16:40.164Z",
      "updatedAt": "2025-05-26T12:16:40.962Z",
      "number": 78856
    },
    {
      "_id": "68345bbcc2f30c001cb27251",
      "ingredients": [
        "643d69a5c3f7b9001cfa093d",
        "643d69a5c3f7b9001cfa0940",
        "643d69a5c3f7b9001cfa093d"
      ],
      "status": "done",
      "name": "Флюоресцентный метеоритный бургер",
      "createdAt": "2025-05-26T12:17:00.721Z",
      "updatedAt": "2025-05-26T12:17:01.479Z",
      "number": 78857
    },
    {
      "_id": "68345c39c2f30c001cb27254",
      "ingredients": [
        "643d69a5c3f7b9001cfa093d",
        "643d69a5c3f7b9001cfa093e",
        "643d69a5c3f7b9001cfa093d"
      ],
      "status": "done",
      "name": "Флюоресцентный люминесцентный бургер",
      "createdAt": "2025-05-26T12:19:05.651Z",
      "updatedAt": "2025-05-26T12:19:06.444Z",
      "number": 78858
    },
    {
      "_id": "68345c58c2f30c001cb27256",
      "ingredients": [
        "643d69a5c3f7b9001cfa093d",
        "643d69a5c3f7b9001cfa0940",
        "643d69a5c3f7b9001cfa093d"
      ],
      "status": "done",
      "name": "Флюоресцентный метеоритный бургер",
      "createdAt": "2025-05-26T12:19:36.909Z",
      "updatedAt": "2025-05-26T12:19:37.581Z",
      "number": 78859
    },
    {
      "_id": "68346c2bc2f30c001cb272a5",
      "ingredients": [
        "643d69a5c3f7b9001cfa093d",
        "643d69a5c3f7b9001cfa093e",
        "643d69a5c3f7b9001cfa0940",
        "643d69a5c3f7b9001cfa0940",
        "643d69a5c3f7b9001cfa093d"
      ],
      "status": "done",
      "name": "Флюоресцентный люминесцентный метеоритный бургер",
      "createdAt": "2025-05-26T13:27:07.912Z",
      "updatedAt": "2025-05-26T13:27:08.635Z",
      "number": 78871
    },
    {
      "_id": "68347ed3c2f30c001cb27323",
      "ingredients": [
        "643d69a5c3f7b9001cfa093d",
        "643d69a5c3f7b9001cfa0941",
        "643d69a5c3f7b9001cfa0947",
        "643d69a5c3f7b9001cfa093d"
      ],
      "status": "done",
      "name": "Флюоресцентный фалленианский био-марсианский бургер",
      "createdAt": "2025-05-26T14:46:43.872Z",
      "updatedAt": "2025-05-26T14:46:44.597Z",
      "number": 78888
    },
    {
      "_id": "68347ef5c2f30c001cb27324",
      "ingredients": [
        "643d69a5c3f7b9001cfa093c",
        "643d69a5c3f7b9001cfa0948",
        "643d69a5c3f7b9001cfa093c"
      ],
      "status": "done",
      "name": "Краторный альфа-сахаридный бургер",
      "createdAt": "2025-05-26T14:47:17.334Z",
      "updatedAt": "2025-05-26T14:47:18.146Z",
      "number": 78889
    }
  ],
  "total": 80355,
  "totalToday": 165
}

